[
  {
    "word": "assignment",
    "definition": [
      { "part_of_speech": "n.", "meaning": "a piece of work you are given to do" }
    ]
  },
  {
    "word": "belief",
    "definition": [
      { "part_of_speech": "n.", "meaning": "a certainty that something is true or real" }
    ]
  },
  {
    "word": "forever",
    "definition": [
      { "part_of_speech": "adv.", "meaning": "for always" }
    ]
  },
  {
    "word": "influence",
    "definition": [
      { "part_of_speech": "n.", "meaning": "the power to affect others" }
    ]
  },
  {
    "word": "joy",
    "definition": [
      { "part_of_speech": "n.", "meaning": "great happiness" }
    ]
  },
  {
    "word": "lean",
    "definition": [
      { "part_of_speech": "v.", "meaning": "to bend your body in a certain direction" }
    ]
  },
  {
    "word": "ordinary",
    "definition": [
      { "part_of_speech": "adj.", "meaning": "normal; not special" }
    ]
  },
  {
    "word": "poet",
    "definition": [
      { "part_of_speech": "n.", "meaning": "a person who writes poems" }
    ]
  },
  {
    "word": "row",
    "definition": [
      { "part_of_speech": "v.", "meaning": "to move a boat using oars" }
    ]
  },
  {
    "word": "thus",
    "definition": [
      { "part_of_speech": "adv.", "meaning": "so" }
    ]
  },
  {
    "word": "ceremony",
    "definition": [
      { "part_of_speech": "n.", "meaning": "a set of formal acts for an occasion" }
    ]
  },
  {
    "word": "emotion",
    "definition": [
      { "part_of_speech": "n.", "meaning": "a strong feeling" }
    ]
  },
  {
    "word": "gentle",
    "definition": [
      { "part_of_speech": "adj.", "meaning": "kind and calm" }
    ]
  },
  {
    "word": "handsome",
    "definition": [
      { "part_of_speech": "adj.", "meaning": "good looking; attractive" }
    ]
  },
  {
    "word": "illustrate",
    "definition": [
      { "part_of_speech": "v.", "meaning": "to draw pictures for a book" }
    ]
  },
  {
    "word": "profession",
    "definition": [
      { "part_of_speech": "n.", "meaning": "a type of job that needs special education" }
    ]
  },
  {
    "word": "prompt",
    "definition": [
      { "part_of_speech": "adj.", "meaning": "on time; punctual" }
    ]
  },
  {
    "word": "reply",
    "definition": [
      { "part_of_speech": "v.", "meaning": "to respond; to answer" }
    ]
  },
  {
    "word": "series",
    "definition": [
      { "part_of_speech": "n.", "meaning": "a set of things that happen one after the other" }
    ]
  },
  {
    "word": "tournament",
    "definition": [
      { "part_of_speech": "n.", "meaning": "a sports competition" }
    ]
  }
]
